{"Version":"1.1","ScriptId":"867946368","Name":"Man in Snow","Category":"Travellers","Microscript":false,"Parts":[{"PartId":"461867136","StepType":2.0,"A":"Don't have no more for you","B":"man1","C":"Okay","V":0.0,"N":"","Condition":{"Key":"None","Operator":1.0,"Value":0.0}},{"PartId":"538956864","StepType":0.0,"A":"By Crom am I glad to see you. In fact take this for spending a little time with me. It gets so lonely here in the cold.","B":"Oh thanks","C":"Don't need your stuff","V":0.0,"N":"","Condition":{"Key":"None","Operator":1.0,"Value":0.0}},{"PartId":"589281920","StepType":4.0,"A":"","B":"","C":"","V":51820428.0,"N":"","Condition":{"Key":"None","Operator":1.0,"Value":0.0}},{"PartId":"971129472","StepType":1.0,"A":"man1","B":"","C":"","V":1.0,"N":"","Condition":{"Key":"None","Operator":1.0,"Value":0.0}},{"PartId":"784234176","StepType":0.0,"A":"Thanks for your time.. Take care now.","B":"Bye","C":"","V":0.0,"N":"","Condition":{"Key":"None","Operator":1.0,"Value":0.0}},{"PartId":"768852800","StepType":3.0,"A":"man1","B":"","C":"","V":3600.0,"N":"","Condition":{"Key":"None","Operator":1.0,"Value":0.0}},{"PartId":"514481024","StepType":22.0,"A":"","B":"","C":"","V":0.0,"N":"","Condition":{"Key":"None","Operator":1.0,"Value":0.0}}]}